[{"id":"d1d6ff96-361b-48ee-a480-ca22dc7c754f","title":"Mouse definitivo","description":"Este es un mouse gamer numero 3","code":"ñlk221","price":10000,"status":true,"stock":11,"category":"Perifericos PC"},{"id":"prueba2","title":"Producto de prueba 2","description":"Este es un mouse gamer numero 3","code":"ñlk221","price":10000,"status":true,"stock":11,"category":"Perifericos PC"},{"id":"prueba3","title":"Producto de prueba 3","description":"Este es un mouse gamer numero 3","code":"ñlk221","price":10000,"status":true,"stock":11,"category":"Perifericos PC"},{"id":"prueba4","title":"Producto de prueba 4","description":"Este es un mouse gamer numero 3","code":"ñlk221","price":10000,"status":true,"stock":11,"category":"Perifericos PC"},{"id":"f981fb1f-41a2-4177-9caa-c0cbf5200fba","title":"Producto de prueba 5","description":"Este es un mouse gamer numero 3","code":"ñlk221","price":10000,"status":true,"stock":11,"category":"Perifericos PC"},{"id":"a8876e3e-d5c9-4394-bc72-ac927359da1e","title":"Producto de prueba 6","description":"Este es un mouse gamer numero 3","code":"ñlk221","price":10000,"status":true,"stock":11,"category":"Perifericos PC"},{"id":"af5183a5-1b45-4b35-9ecd-fe262f57f64d","title":"Mouse definitivo","description":"Este es un mouse gamer numero 3","code":"ñlk221","price":10000,"status":true,"stock":11,"category":"Perifericos PC","thumbnails":"/Aca/va/una/ruta/EnTeoria"},{"id":"prueba1","title":"Se modifico el title de prueba 1 otra vez","description":"Este es un mouse gamer numero 3","code":"CodigoEspecialModificado","price":10000,"status":true,"stock":11,"category":"Perifericos PC","precio":999999}]